dynmen/__init__.py
dynmen/common.py
dynmen/dmenu.py
dynmen/menu.py
dynmen/rofi.py
dynmen/cmd/__init__.py
dynmen/cmd/async.py
dynmen/cmd/async_py3.py
dynmen/cmd/blocking.py
dynmen/cmd/futures.py
dynmen-0.1.5.dist-info/DESCRIPTION.rst
dynmen-0.1.5.dist-info/METADATA
dynmen-0.1.5.dist-info/RECORD
dynmen-0.1.5.dist-info/WHEEL
dynmen-0.1.5.dist-info/metadata.json
dynmen-0.1.5.dist-info/top_level.txt
