Metadata-Version: 2.0
Name: dynmen
Version: 0.1.5
Summary: dynmen is an interface to dynamic menus, like dmenu, rofi, or fzf.
Home-page: https://github.com/frostidaho/dynmen
Author: Idaho Frost
Author-email: frostidaho@gmail.com
License: UNKNOWN
Platform: UNKNOWN
Classifier: License :: OSI Approved :: MIT License
Classifier: Programming Language :: Python :: 2.7
Classifier: Programming Language :: Python :: 3.3
Classifier: Programming Language :: Python :: 3.4
Classifier: Programming Language :: Python :: 3.5
Classifier: Programming Language :: Python :: 3.6
Classifier: Programming Language :: Python :: Implementation :: CPython
Classifier: Operating System :: Unix
